{
  "_class": "group",
  "booleanOperation": -1,
  "clippingMaskMode": 0,
  "do_objectID": "ACC223D6-8171-467F-A5C5-1EE056D6C488",
  "exportOptions": {
    "_class": "exportOptions",
    "exportFormats": [
    ],
    "includedLayerIds": [
    ],
    "layerOptions": 0,
    "shouldTrim": false
  },
  "frame": {
    "_class": "rect",
    "constrainProportions": false,
    "height": 995,
    "width": 951,
    "x": 230,
    "y": 80
  },
  "groupLayout": {
    "_class": "MSImmutableFreeformGroupLayout"
  },
  "hasClickThrough": false,
  "hasClippingMask": false,
  "isFixedToViewport": false,
  "isFlippedHorizontal": false,
  "isFlippedVertical": false,
  "isLocked": false,
  "isVisible": true,
  "layerListExpandedType": 2,
  "layers": [
    {
      "class": "group",
      "id": "CFF53662-AAD1-4B76-94CD-045C3B137BC6"
    },
    {
      "class": "group",
      "id": "11B5401D-42A3-4C19-B730-DDD0E77A4E3B"
    },
    {
      "class": "group",
      "id": "86306EEC-DC29-4299-A0B0-7FA9B1571CCA"
    },
    {
      "class": "group",
      "id": "397988CA-7DD5-4F52-823C-8B1AAE216442"
    },
    {
      "class": "group",
      "id": "CE5684C6-5370-4E6F-A2F1-B02EFDFB38EF"
    },
    {
      "class": "group",
      "id": "B96DFD1C-2D65-459E-AE0B-4B5C3E7FFC24"
    },
    {
      "class": "group",
      "id": "9AC37BF1-2FFD-4163-87BE-4A663DCE9A6A"
    }
  ],
  "name": "Group 7",
  "nameIsFixed": false,
  "resizingConstraint": 63,
  "resizingType": 0,
  "rotation": 0,
  "shouldBreakMaskChain": false,
  "style": {
    "_class": "style",
    "blur": {
      "_class": "blur",
      "center": "{0.5, 0.5}",
      "isEnabled": false,
      "motionAngle": 0,
      "radius": 10,
      "saturation": 1,
      "type": 0
    },
    "borderOptions": {
      "_class": "borderOptions",
      "dashPattern": [
      ],
      "isEnabled": true,
      "lineCapStyle": 0,
      "lineJoinStyle": 0
    },
    "borders": [
    ],
    "colorControls": {
      "_class": "colorControls",
      "brightness": 0,
      "contrast": 1,
      "hue": 0,
      "isEnabled": false,
      "saturation": 1
    },
    "contextSettings": {
      "_class": "graphicsContextSettings",
      "blendMode": 0,
      "opacity": 1
    },
    "do_objectID": "B8D0455D-3A4F-4412-AD85-1DD3D926813E",
    "endMarkerType": 0,
    "fills": [
    ],
    "innerShadows": [
    ],
    "miterLimit": 10,
    "shadows": [
    ],
    "startMarkerType": 0,
    "windingRule": 1
  },
  "userInfo": {
    "com.animaapp.stc-sketch-plugin": {
      "kModelPropertiesKey": {
        "align": 2,
        "isCollapsing": 1,
        "resizesContainer": 1,
        "spacing": 20,
        "stackType": 0
      },
      "kViewTypeKey": "ADModelStackView"
    }
  }
}