{
  "_class": "symbolInstance",
  "booleanOperation": -1,
  "clippingMaskMode": 0,
  "do_objectID": "9DB79EBB-2353-48E6-856C-A0961F42C4A5",
  "exportOptions": {
    "_class": "exportOptions",
    "exportFormats": [
    ],
    "includedLayerIds": [
    ],
    "layerOptions": 0,
    "shouldTrim": false
  },
  "frame": {
    "_class": "rect",
    "constrainProportions": false,
    "height": 40,
    "width": 971,
    "x": 0,
    "y": 187
  },
  "hasClippingMask": false,
  "horizontalSpacing": 0,
  "isFixedToViewport": false,
  "isFlippedHorizontal": false,
  "isFlippedVertical": false,
  "isLocked": false,
  "isVisible": true,
  "layerListExpandedType": 0,
  "name": "users/table copy 4",
  "nameIsFixed": false,
  "overrideValues": [
    {
      "_class": "overrideValue",
      "overrideName": "8DC50623-76A5-403B-B5FC-B3726E3F2BBB_stringValue",
      "value": "Christina"
    },
    {
      "_class": "overrideValue",
      "overrideName": "F9E8D870-AABB-48DD-B202-AF6992B0C020_stringValue",
      "value": "cmoraless@stumbleupon.com"
    },
    {
      "_class": "overrideValue",
      "overrideName": "08EFB9A7-0633-4C60-9EFE-05919B46EAB0_stringValue",
      "value": "Christina Morales"
    },
    {
      "_class": "overrideValue",
      "overrideName": "E2CA5CB1-C396-4BA9-B55B-C08A4AE8F52A_stringValue",
      "value": "4-(319)232-1760"
    },
    {
      "_class": "overrideValue",
      "overrideName": "7F3C91F8-9D71-4E76-A34A-673489222E8C_symbolID",
      "value": "0B797345-CCF7-4ADC-A8FA-A3123E9D2EB5"
    }
  ],
  "resizingConstraint": 63,
  "resizingType": 0,
  "rotation": 0,
  "scale": 1,
  "shouldBreakMaskChain": false,
  "style": {
    "_class": "style",
    "blur": {
      "_class": "blur",
      "center": "{0.5, 0.5}",
      "isEnabled": false,
      "motionAngle": 0,
      "radius": 10,
      "saturation": 1,
      "type": 0
    },
    "borderOptions": {
      "_class": "borderOptions",
      "dashPattern": [
      ],
      "isEnabled": true,
      "lineCapStyle": 0,
      "lineJoinStyle": 0
    },
    "borders": [
    ],
    "colorControls": {
      "_class": "colorControls",
      "brightness": 0,
      "contrast": 1,
      "hue": 0,
      "isEnabled": true,
      "saturation": 1
    },
    "contextSettings": {
      "_class": "graphicsContextSettings",
      "blendMode": 0,
      "opacity": 1
    },
    "do_objectID": "1FDDF308-0069-4200-B430-FF89BD539D8D",
    "endMarkerType": 0,
    "fills": [
    ],
    "innerShadows": [
    ],
    "miterLimit": 10,
    "shadows": [
    ],
    "startMarkerType": 0,
    "windingRule": 1
  },
  "symbolID": "C6763575-D6BC-470E-97C6-6DC737D82A0E",
  "verticalSpacing": 0
}