{
  "_class": "group",
  "booleanOperation": 0,
  "clippingMaskMode": 0,
  "do_objectID": "4D2840F7-E580-4808-9208-4EC181D8A2BD",
  "exportOptions": {
    "_class": "exportOptions",
    "exportFormats": [
    ],
    "includedLayerIds": [
    ],
    "layerOptions": 0,
    "shouldTrim": false
  },
  "frame": {
    "_class": "rect",
    "constrainProportions": false,
    "height": 424,
    "width": 425,
    "x": 430,
    "y": 138
  },
  "groupLayout": {
    "_class": "MSImmutableFreeformGroupLayout"
  },
  "hasClickThrough": true,
  "hasClippingMask": false,
  "isFixedToViewport": false,
  "isFlippedHorizontal": false,
  "isFlippedVertical": false,
  "isLocked": false,
  "isVisible": false,
  "layerListExpandedType": 0,
  "layers": [
    {
      "class": "shapePath",
      "id": "1AA8966F-4C79-4E9D-B6C1-1934EDEB935F"
    },
    {
      "class": "group",
      "id": "6B81C3CD-246F-4A94-9426-89818C2440BE"
    },
    {
      "class": "group",
      "id": "B9DC3936-1697-4284-849D-957187B462D3"
    },
    {
      "class": "text",
      "id": "068CDB19-B0CB-44DE-B71C-2A2EC4BE6288"
    },
    {
      "class": "shapePath",
      "id": "D6BDD3D7-C852-4C47-BD90-65AA62E884E1"
    },
    {
      "class": "text",
      "id": "0ED5BD95-BD54-4D72-BF60-BA3DD7AC088F"
    },
    {
      "class": "group",
      "id": "8A9FB901-0632-4AB4-9D42-F93B77B6BEA4"
    },
    {
      "class": "bitmap",
      "id": "87066F6F-5CE0-4EE1-ABAD-FBB3337C1F87"
    }
  ],
  "name": "LOGIN copy",
  "nameIsFixed": false,
  "resizingConstraint": 63,
  "resizingType": 0,
  "rotation": 0,
  "shouldBreakMaskChain": false,
  "style": {
    "_class": "style",
    "blur": {
      "_class": "blur",
      "center": "{0.5, 0.5}",
      "isEnabled": false,
      "motionAngle": 0,
      "radius": 10,
      "saturation": 1,
      "type": 0
    },
    "borderOptions": {
      "_class": "borderOptions",
      "dashPattern": [
      ],
      "isEnabled": true,
      "lineCapStyle": 0,
      "lineJoinStyle": 0
    },
    "borders": [
    ],
    "colorControls": {
      "_class": "colorControls",
      "brightness": 0,
      "contrast": 1,
      "hue": 0,
      "isEnabled": true,
      "saturation": 1
    },
    "contextSettings": {
      "_class": "graphicsContextSettings",
      "blendMode": 0,
      "opacity": 1
    },
    "do_objectID": "178E8605-3F05-422C-A7D8-664FD1FA8F6C",
    "endMarkerType": 0,
    "fills": [
    ],
    "innerShadows": [
    ],
    "miterLimit": 10,
    "shadows": [
    ],
    "startMarkerType": 0,
    "windingRule": 1
  },
  "userInfo": {
    "com.animaapp.stc-sketch-plugin": {
      "kModelPropertiesKey": {
      }
    }
  }
}