{
  "_class": "group",
  "booleanOperation": -1,
  "clippingMaskMode": 0,
  "do_objectID": "ADB2B8CF-96C7-45B8-A46D-E62216F39D40",
  "exportOptions": {
    "_class": "exportOptions",
    "exportFormats": [
    ],
    "includedLayerIds": [
    ],
    "layerOptions": 0,
    "shouldTrim": false
  },
  "frame": {
    "_class": "rect",
    "constrainProportions": false,
    "height": 150,
    "width": 400,
    "x": 0,
    "y": 5
  },
  "groupLayout": {
    "_class": "MSImmutableFreeformGroupLayout"
  },
  "hasClickThrough": false,
  "hasClippingMask": false,
  "isFixedToViewport": false,
  "isFlippedHorizontal": false,
  "isFlippedVertical": false,
  "isLocked": false,
  "isVisible": true,
  "layerListExpandedType": 2,
  "layers": [
    {
      "class": "symbolInstance",
      "id": "2296E2F1-9342-4B66-BEDF-1C61EECAE316"
    },
    {
      "class": "symbolInstance",
      "id": "0E43070C-0A59-40C0-BAD8-B90D04616546"
    },
    {
      "class": "symbolInstance",
      "id": "806712DE-FF26-4105-94A2-596564618BC5"
    },
    {
      "class": "symbolInstance",
      "id": "35034C58-F654-427A-AA33-57D1CC8158C2"
    },
    {
      "class": "symbolInstance",
      "id": "F1F44916-A1FC-4A16-B52B-D32C726B5B9F"
    }
  ],
  "name": "dropdown / item copy 6",
  "nameIsFixed": false,
  "resizingConstraint": 63,
  "resizingType": 0,
  "rotation": 0,
  "shouldBreakMaskChain": false,
  "style": {
    "_class": "style",
    "blur": {
      "_class": "blur",
      "center": "{0.5, 0.5}",
      "isEnabled": false,
      "motionAngle": 0,
      "radius": 10,
      "saturation": 1,
      "type": 0
    },
    "borderOptions": {
      "_class": "borderOptions",
      "dashPattern": [
      ],
      "isEnabled": true,
      "lineCapStyle": 0,
      "lineJoinStyle": 0
    },
    "borders": [
    ],
    "colorControls": {
      "_class": "colorControls",
      "brightness": 0,
      "contrast": 1,
      "hue": 0,
      "isEnabled": true,
      "saturation": 1
    },
    "contextSettings": {
      "_class": "graphicsContextSettings",
      "blendMode": 0,
      "opacity": 1
    },
    "do_objectID": "925D07C2-8615-4361-ADE6-846AC3278534",
    "endMarkerType": 0,
    "fills": [
    ],
    "innerShadows": [
    ],
    "miterLimit": 10,
    "shadows": [
    ],
    "startMarkerType": 0,
    "windingRule": 1
  },
  "userInfo": {
    "com.animaapp.stc-sketch-plugin": {
      "kModelPropertiesKey": {
        "align": 0,
        "isCollapsing": 1,
        "resizesContainer": 1,
        "spacing": 0,
        "stackType": 0
      },
      "kViewTypeKey": "ADModelStackView"
    }
  }
}