{
  "_class": "shapePath",
  "booleanOperation": 0,
  "clippingMaskMode": 0,
  "do_objectID": "C25AFC9D-F039-4E4D-A7A1-7A3918294CB3",
  "edited": false,
  "exportOptions": {
    "_class": "exportOptions",
    "exportFormats": [
    ],
    "includedLayerIds": [
    ],
    "layerOptions": 0,
    "shouldTrim": false
  },
  "frame": {
    "_class": "rect",
    "constrainProportions": false,
    "height": 23,
    "width": 23,
    "x": 0,
    "y": 0
  },
  "hasClippingMask": false,
  "isClosed": true,
  "isFixedToViewport": false,
  "isFlippedHorizontal": false,
  "isFlippedVertical": false,
  "isLocked": false,
  "isVisible": true,
  "layerListExpandedType": 0,
  "name": "Shape sp-8258-0",
  "nameIsFixed": false,
  "pointRadiusBehaviour": 0,
  "points": [
    {
      "_class": "curvePoint",
      "cornerRadius": 0,
      "curveFrom": "{0.406445, 0.42895299999999997}",
      "curveMode": 2,
      "curveTo": "{0.39229799999999998, 0.41480099999999998}",
      "hasCurveFrom": true,
      "hasCurveTo": true,
      "point": "{0.406445, 0.42895299999999997}"
    },
    {
      "_class": "curvePoint",
      "cornerRadius": 0,
      "curveFrom": "{0.57431399999999999, 0.59682100000000005}",
      "curveMode": 2,
      "curveTo": "{0.56016699999999997, 0.58266799999999996}",
      "hasCurveFrom": true,
      "hasCurveTo": true,
      "point": "{0.56016699999999997, 0.58266799999999996}"
    },
    {
      "_class": "curvePoint",
      "cornerRadius": 0,
      "curveFrom": "{0.56016699999999997, 0.633911}",
      "curveMode": 2,
      "curveTo": "{0.57431399999999999, 0.61976399999999998}",
      "hasCurveFrom": true,
      "hasCurveTo": true,
      "point": "{0.56016699999999997, 0.633911}"
    },
    {
      "_class": "curvePoint",
      "cornerRadius": 0,
      "curveFrom": "{0.49477900000000002, 0.69929799999999998}",
      "curveMode": 2,
      "curveTo": "{0.50892599999999999, 0.68515000000000004}",
      "hasCurveFrom": true,
      "hasCurveTo": true,
      "point": "{0.50892599999999999, 0.68515000000000004}"
    },
    {
      "_class": "curvePoint",
      "cornerRadius": 0,
      "curveFrom": "{0.45768599999999998, 0.68515000000000004}",
      "curveMode": 2,
      "curveTo": "{0.471833, 0.69929799999999998}",
      "hasCurveFrom": true,
      "hasCurveTo": true,
      "point": "{0.45768599999999998, 0.68515000000000004}"
    },
    {
      "_class": "curvePoint",
      "cornerRadius": 0,
      "curveFrom": "{0.28981699999999999, 0.51728200000000002}",
      "curveMode": 2,
      "curveTo": "{0.30396800000000002, 0.53143399999999996}",
      "hasCurveFrom": true,
      "hasCurveTo": true,
      "point": "{0.30396800000000002, 0.53143399999999996}"
    },
    {
      "_class": "curvePoint",
      "cornerRadius": 0,
      "curveFrom": "{0.30396800000000002, 0.48019099999999998}",
      "curveMode": 2,
      "curveTo": "{0.28981699999999999, 0.49433899999999997}",
      "hasCurveFrom": true,
      "hasCurveTo": true,
      "point": "{0.30396800000000002, 0.48019099999999998}"
    },
    {
      "_class": "curvePoint",
      "cornerRadius": 0,
      "curveFrom": "{0.36935499999999999, 0.41480099999999998}",
      "curveMode": 2,
      "curveTo": "{0.35520499999999999, 0.42895299999999997}",
      "hasCurveFrom": true,
      "hasCurveTo": true,
      "point": "{0.35520499999999999, 0.42895299999999997}"
    }
  ],
  "resizingConstraint": 63,
  "resizingType": 0,
  "rotation": 0,
  "shouldBreakMaskChain": false,
  "style": {
    "_class": "style",
    "blur": {
      "_class": "blur",
      "center": "{0.5, 0.5}",
      "isEnabled": false,
      "motionAngle": 0,
      "radius": 10,
      "saturation": 1,
      "type": 0
    },
    "borderOptions": {
      "_class": "borderOptions",
      "dashPattern": [
      ],
      "isEnabled": true,
      "lineCapStyle": 0,
      "lineJoinStyle": 0
    },
    "borders": [
    ],
    "colorControls": {
      "_class": "colorControls",
      "brightness": 0,
      "contrast": 1,
      "hue": 0,
      "isEnabled": true,
      "saturation": 1
    },
    "contextSettings": {
      "_class": "graphicsContextSettings",
      "blendMode": 0,
      "opacity": 1
    },
    "do_objectID": "3718B796-5947-4345-A535-FFAD9FAED367",
    "endMarkerType": 0,
    "fills": [
      {
        "_class": "fill",
        "color": {
          "_class": "color",
          "alpha": 1,
          "blue": 0.6862745,
          "green": 0.6627451,
          "red": 0.6117647
        },
        "contextSettings": {
          "_class": "graphicsContextSettings",
          "blendMode": 0,
          "opacity": 1
        },
        "fillType": 0,
        "gradient": {
          "_class": "gradient",
          "elipseLength": 0,
          "from": "{0.5, 0}",
          "gradientType": 0,
          "stops": [
            {
              "_class": "gradientStop",
              "color": {
                "_class": "color",
                "alpha": 1,
                "blue": 1,
                "green": 1,
                "red": 1
              },
              "position": 0
            },
            {
              "_class": "gradientStop",
              "color": {
                "_class": "color",
                "alpha": 1,
                "blue": 0,
                "green": 0,
                "red": 0
              },
              "position": 1
            }
          ],
          "to": "{0.5, 1}"
        },
        "isEnabled": true,
        "noiseIndex": 0,
        "noiseIntensity": 0,
        "patternFillType": 1,
        "patternTileScale": 1
      }
    ],
    "innerShadows": [
    ],
    "miterLimit": 10,
    "shadows": [
    ],
    "startMarkerType": 0,
    "windingRule": 1
  }
}