{
  "_class": "group",
  "booleanOperation": -1,
  "clippingMaskMode": 0,
  "do_objectID": "FDF23C05-7DF9-429D-9F71-B71B7EC599D2",
  "exportOptions": {
    "_class": "exportOptions",
    "exportFormats": [
    ],
    "includedLayerIds": [
    ],
    "layerOptions": 0,
    "shouldTrim": false
  },
  "frame": {
    "_class": "rect",
    "constrainProportions": false,
    "height": 270,
    "width": 174,
    "x": 0,
    "y": 5
  },
  "groupLayout": {
    "_class": "MSImmutableFreeformGroupLayout"
  },
  "hasClickThrough": false,
  "hasClippingMask": false,
  "isFixedToViewport": false,
  "isFlippedHorizontal": false,
  "isFlippedVertical": false,
  "isLocked": false,
  "isVisible": true,
  "layerListExpandedType": 0,
  "layers": [
    {
      "class": "symbolInstance",
      "id": "F9311450-68A4-4FD9-AC82-3AE5F6D8D6A0"
    },
    {
      "class": "symbolInstance",
      "id": "BF405C46-4AA6-4633-8207-2F3EB3BE1B4A"
    },
    {
      "class": "symbolInstance",
      "id": "66F63C39-E5EB-40DF-A046-E1D6DB6279D2"
    },
    {
      "class": "symbolInstance",
      "id": "3C321108-D935-4004-9B89-C1AC74D0DBB7"
    },
    {
      "class": "symbolInstance",
      "id": "AE153D07-45AC-484D-A4C7-78B741AED2D2"
    },
    {
      "class": "symbolInstance",
      "id": "DD92EA2E-9460-4EB5-9674-91152ED05419"
    },
    {
      "class": "symbolInstance",
      "id": "4CED6A1D-35D1-42C0-86FB-B67C92BB74C9"
    },
    {
      "class": "symbolInstance",
      "id": "722B5157-8C6B-45D9-9394-BBD7F363C2DC"
    },
    {
      "class": "symbolInstance",
      "id": "3BD0577E-CE07-433C-9F83-0646EE101E27"
    }
  ],
  "name": "dropdown / item copy 6",
  "nameIsFixed": false,
  "resizingConstraint": 63,
  "resizingType": 0,
  "rotation": 0,
  "shouldBreakMaskChain": false,
  "style": {
    "_class": "style",
    "blur": {
      "_class": "blur",
      "center": "{0.5, 0.5}",
      "isEnabled": false,
      "motionAngle": 0,
      "radius": 10,
      "saturation": 1,
      "type": 0
    },
    "borderOptions": {
      "_class": "borderOptions",
      "dashPattern": [
      ],
      "isEnabled": true,
      "lineCapStyle": 0,
      "lineJoinStyle": 0
    },
    "borders": [
    ],
    "colorControls": {
      "_class": "colorControls",
      "brightness": 0,
      "contrast": 1,
      "hue": 0,
      "isEnabled": true,
      "saturation": 1
    },
    "contextSettings": {
      "_class": "graphicsContextSettings",
      "blendMode": 0,
      "opacity": 1
    },
    "do_objectID": "4C17BD02-3A10-4BC2-BDF2-EB604F170DC2",
    "endMarkerType": 0,
    "fills": [
    ],
    "innerShadows": [
    ],
    "miterLimit": 10,
    "shadows": [
    ],
    "startMarkerType": 0,
    "windingRule": 1
  },
  "userInfo": {
    "com.animaapp.stc-sketch-plugin": {
      "kModelPropertiesKey": {
        "align": 0,
        "isCollapsing": 1,
        "resizesContainer": 1,
        "spacing": 0,
        "stackType": 0
      },
      "kViewTypeKey": "ADModelStackView"
    }
  }
}