{
  "_class": "group",
  "booleanOperation": -1,
  "clippingMaskMode": 0,
  "do_objectID": "8425ABEF-E1F1-4C20-9F84-F57E1718D715",
  "exportOptions": {
    "_class": "exportOptions",
    "exportFormats": [
    ],
    "includedLayerIds": [
    ],
    "layerOptions": 0,
    "shouldTrim": false
  },
  "frame": {
    "_class": "rect",
    "constrainProportions": false,
    "height": 165,
    "width": 174,
    "x": 285,
    "y": 106
  },
  "groupLayout": {
    "_class": "MSImmutableFreeformGroupLayout"
  },
  "hasClickThrough": false,
  "hasClippingMask": false,
  "isFixedToViewport": false,
  "isFlippedHorizontal": false,
  "isFlippedVertical": false,
  "isLocked": false,
  "isVisible": true,
  "layerListExpandedType": 2,
  "layers": [
    {
      "class": "rectangle",
      "id": "7D41F5F8-E875-439E-A269-90E0F3471E15"
    },
    {
      "class": "group",
      "id": "8BDE1477-072D-41B5-82D1-2F698FB4E27D"
    }
  ],
  "name": "dropdown copy",
  "nameIsFixed": true,
  "resizingConstraint": 63,
  "resizingType": 0,
  "rotation": 0,
  "shouldBreakMaskChain": false,
  "style": {
    "_class": "style",
    "blur": {
      "_class": "blur",
      "center": "{0.5, 0.5}",
      "isEnabled": false,
      "motionAngle": 0,
      "radius": 10,
      "saturation": 1,
      "type": 0
    },
    "borderOptions": {
      "_class": "borderOptions",
      "dashPattern": [
      ],
      "isEnabled": true,
      "lineCapStyle": 0,
      "lineJoinStyle": 0
    },
    "borders": [
    ],
    "colorControls": {
      "_class": "colorControls",
      "brightness": 0,
      "contrast": 1,
      "hue": 0,
      "isEnabled": true,
      "saturation": 1
    },
    "contextSettings": {
      "_class": "graphicsContextSettings",
      "blendMode": 0,
      "opacity": 1
    },
    "do_objectID": "E77EACC1-E3D6-42AF-B6B2-AD1506472E75",
    "endMarkerType": 0,
    "fills": [
    ],
    "innerShadows": [
    ],
    "miterLimit": 10,
    "shadows": [
    ],
    "startMarkerType": 0,
    "windingRule": 1
  },
  "userInfo": {
    "com.animaapp.stc-sketch-plugin": {
      "kModelPropertiesKey": {
        "padding": {
          "bottom": 5,
          "left": 0,
          "modelID": "viewPadding_4342c4b4-388d-4c83-903b-e6394f458dbd",
          "model_class": "ADModelViewPadding",
          "model_version": 0,
          "right": 0,
          "top": 10
        }
      }
    }
  }
}